Workbook

Sheet Premissas
A1: Prospecta Instagram — Premissas (edite só as células azuis/amarelas)
A2: Legenda: texto AZUL = número que você pode mudar · fundo AMARELO = premissa-chave · texto preto = fórmula · verde = puxado de outra aba
A4: Premissa | B4: Valor | C4: Unidade | D4: Fonte / observação
A5: Câmbio (R$ por US$) | B5: 5.5 | C5: R$/US$ | D5: Estimativa. Ajuste para o câmbio do dia.
A6: Preço Claude Sonnet 5.5 — entrada | B6: 2 | C6: US$ / 1M tokens | D6: Tabela de preços da Anthropic (referência cacheada em 25/09/2026).
A7: Preço Claude Sonnet 5.5 — saída | B7: 10 | C7: US$ / 1M tokens | D7: Tabela de preços da Anthropic (referência cacheada em 25/09/2026).
A8: Preço Claude Haiku 4.5 — entrada | B8: 1 | C8: US$ / 1M tokens | D8: Tabela de preços da Anthropic (referência cacheada em 25/09/2026).
A9: Preço Claude Haiku 4.5 — saída | B9: 5 | C9: US$ / 1M tokens | D9: Tabela de preços da Anthropic (referência cacheada em 25/09/2026).
A10: Economia na entrada com cache de prompt/lote | B10: 0.5 | C10: % | D10: O playbook e o perfil do cliente ideal se repetem em toda chamada; com cache de prompt, a leitura repetida sai bem mais barata. 50% é uma estimativa conservadora.
A11: Leads abordados por mês (por usuário) | B11: 400 | C11: leads | D11: ~20 DMs manuais por dia útil: volume seguro para não parecer spam no Instagram.
A12: Follow-ups por lead sem resposta | B12: 2 | C12: mensagens | D12: Cadência D+2 e D+5 (o 3º toque é opcional).
A13: Taxa de resposta das DMs | B13: 0.15 | C13: % | D13: Hipótese inicial de abordagem personalizada. Meça no seu teste e ajuste.
A14: Rodadas de conversa por lead que responde | B14: 4 | C14: rodadas | D14: Diagnóstico → valor → objeção → convite/oferta.
A15: Taxa de conversão resposta → venda | B15: 0.1 | C15: % | D15: Hipótese. Serve só para estimar o retorno, não o custo.
A16: Ticket médio do SEU produto (uso próprio) | B16: 497 | C16: R$ | D16: Preencha com o preço do seu infoproduto ou micro SaaS.
... A22: Verba mensal de marketing (cenário de venda) | B22: 1000 | C22: R$/mês | D22: Tráfego pago, conteúdo ou parcerias. Coloque 0 se for só orgânico.

Sheet IA por lead
A1: Custo da inteligência por lead (o que a IA faz em cada etapa)
A3: Etapa da IA | B3: Modelo | C3: Tokens de entrada | D3: Tokens de saída | E3: Vezes por lead | F3: Custo por vez (US$) | G3: Custo por lead (US$) | H3: O que faz
A4: 1. Análise do perfil (bio, posts, sinais de compra) | B4: Haiku | C4: 3500 | D4: 600 | E4: =1 -> 1 | F4: =IF(B4="Sonnet",(C4*(1-Premissas!$B$10)*Premissas!$B$6+D4*Premissas!$B$7)/1000000,(C4*(1-Premissas!$B$10)*Premissas!$B$8+D4*Premissas!$B$9)/1000000) -> 0.00475 | G4: =F4*E4 -> 0.00475 | H4: Lê bio, link e últimas legendas; classifica estágio, dor provável, nota de fit e temperatura.
A5: 2. DM de abertura personalizada | B5: Sonnet | C5: 2500 | D5: 300 | E5: =1 -> 1 | F5: =IF(B5="Sonnet",(C5*(1-Premissas!$B$10)*Premissas!$B$6+D5*Premissas!$B$7)/1000000,(C5*(1-Premissas!$B$10)*Premissas!$B$8+D5*Premissas!$B$9)/1000000) -> 0.0055 | G5: =F5*E5 -> 0.0055 | H5: Escreve a 1ª mensagem com gancho específico, sem pitch, terminando em pergunta.
A6: 3. Follow-ups (quem não respondeu) | B6: Haiku | C6: 2000 | D6: 250 | E6: =Premissas!$B$12*(1-Premissas!$B$13) -> 1.7 | F6: =IF(B6="Sonnet",(C6*(1-Premissas!$B$10)*Premissas!$B$6+D6*Premissas!$B$7)/1000000,(C6*(1-Premissas!$B$10)*Premissas!$B$8+D6*Premissas!$B$9)/1000000) -> 0.00225 | G6: =F6*E6 -> 0.003825 | H6: Mensagens novas trazendo valor, sem cobrar resposta.
A7: 4. Conversa: ler resposta e sugerir a próxima mensagem | B7: Sonnet | C7: 3000 | D7: 450 | E7: =Premissas!$B$13*Premissas!$B$14 -> 0.6 | F7: =IF(B7="Sonnet",(C7*(1-Premissas!$B$10)*Premissas!$B$6+D7*Premissas!$B$7)/1000000,(C7*(1-Premissas!$B$10)*Premissas!$B$8+D7*Premissas!$B$9)/1000000) -> 0.0075 | G7: =F7*E7 -> 0.0045 | H7: Classifica a resposta, trata objeções e conduz até a call ou o link de checkout.
A8: 5. Placar e aprendizado (o que converte) | B8: Haiku | C8: 1500 | D8: 200 | E8: =1 -> 1 | F8: =IF(B8="Sonnet",(C8*(1-Premissas!$B$10)*Premissas!$B$6+D8*Premissas!$B$7)/1000000,(C8*(1-Premissas!$B$10)*Premissas!$B$8+D8*Premissas!$B$9)/1000000) -> 0.00175 | G8: =F8*E8 -> 0.00175 | H8: Registra o resultado e ajusta as melhores aberturas e ganchos do seu nicho.
A9: Custo de IA por lead (US$) | G9: =SUM(G4:G8) -> 0.020325
A10: Custo de IA por lead (R$) | G10: =G9*Premissas!$B$5 -> 0.1117875
A11: Custo de IA por usuário/mês (R$) | G11: =G10*Premissas!$B$11 -> 44.715
A13: Tokens são estimativas do tamanho dos textos (1 token ≈ 3/4 de palavra). Os modelos podem ser trocados na coluna B (Sonnet ou Haiku).

Sheet Uso próprio
A1: Cenário 1 — Uso próprio (1 usuária: você testando)
A3: Custos
A4: Item | B4: Custo inicial (R$) | C4: Custo mensal (R$) | D4: Obrigatório? | E4: Observação / fonte
A5: Hospedagem do app (Netlify, plano gratuito) | B5: 0 | C5: 0 | D5: Sim | E5: O plano gratuito atende 1 usuária.
A6: Banco de dados e login (Supabase Free) | B6: 0 | C6: 0 | D6: Sim | E6: Grátis até 500 MB. O projeto pausa após 7 dias sem uso (basta abrir o app).
A7: IA — Claude (análise, DMs e conversa) | B7: =5*Premissas!$B$5 -> 27.5 | C7: ='IA por lead'!$G$11 -> 44.715 | D7: Sim | E7: Inicial = US$ 5 de crédito mínimo. Mensal = custo por lead × leads/mês (aba IA por lead).
A8: App da Meta / API do Instagram | B8: 0 | C8: 0 | D8: Sim | E8: Gratuito. Para uso só na sua conta, o app fica em modo de desenvolvimento, sem revisão da Meta.
A9: Automação comentário → DM (ChatFyre) | B9: 0 | C9: 0 | D9: Opcional | E9: Você já tem o ChatFyre conectado. Coloque aqui o valor do seu plano.
A10: Domínio próprio (.com.br, registro.br) | B10: 40 | C10: 0 | D10: Opcional | E10: ~R$ 40/ano. Pode usar o endereço grátis .netlify.app no teste.
A11: E-mails (Resend, plano gratuito) | B11: 0 | C11: 0 | D11: Opcional | E11: Grátis até 3.000 e-mails/mês. Para 1 usuária, o e-mail do Supabase basta.
A12: Assinatura do Claude (para eu desenvolver) | B12: 0 | C12: 0 | D12: — | E12: Você já paga. Não é custo novo do projeto.
A13: TOTAL | B13: =SUM(B5:B12) -> 67.5 | C13: =SUM(C5:C12) -> 44.715
A15: Retorno estimado do teste (por mês)
A16: Leads abordados | B16: =Premissas!$B$11 -> 400
A17: Respostas esperadas | B17: =Premissas!$B$11*Premissas!$B$13 -> 60
A18: Vendas esperadas | B18: =Premissas!$B$11*Premissas!$B$13*Premissas!$B$15 -> 6
A19: Faturamento estimado (R$) | B19: =Premissas!$B$11*Premissas!$B$13*Premissas!$B$15*Premissas!$B$16 -> 2982
A20: Custo mensal total (R$) | B20: =C13 -> 44.715
A21: Retorno sobre o custo (x) | B21: =IFERROR(B19/B20,0) -> 66.689031
A23: As taxas de resposta e de conversão são hipóteses (aba Premissas). Troque pelos números reais do seu teste.

Sheet Venda
A1: Cenário 2 — Vender o micro SaaS
A3: Custos fixos e de lançamento
A4: Item | B4: Custo inicial (R$) | C4: Custo mensal (R$) | D4: Obrigatório? | E4: Observação / fonte
A5: Abertura de empresa (ME, Simples Nacional) | B5: 500 | C5: 0 | D5: Sim | E5: Estimativa: taxas da Junta e do município. Muitos contadores online abrem sem custo. Software não pode ser MEI (CNAE 6201/6203).
A6: Contador | B6: 0 | C6: 250 | D6: Sim | E6: Estimativa de contabilidade online para ME de serviços.
A7: Termos de uso, privacidade e contrato (advogado) | B7: 1500 | C7: 0 | D7: Sim | E7: Estimativa. Inclui a revisão LGPD das páginas /privacidade e /termos.
A8: Registro de marca no INPI (1 classe) | B8: 450 | C8: 0 | D8: Recomendado | E8: Estimativa com o desconto de ME. Conferir a tabela de retribuições do INPI.
A9: Domínio .com.br | B9: 40 | C9: 0 | D9: Sim | E9: registro.br, ~R$ 40/ano.
A10: Verificação do negócio + revisão do app na Meta | B10: 0 | C10: 0 | D10: Sim | E10: Gratuita, mas leva de 1 a 4 semanas. Exige política de privacidade publicada e CNPJ.
A11: Supabase Pro | B11: 0 | C11: =25*Premissas!$B$5 -> 137.5 | D11: Sim | E11: US$ 25/mês: 8 GB de banco, 100 mil usuários ativos, sem pausa. Fonte: guias de preço 2026; conferir supabase.com/pricing.
A12: Netlify (plano pago) | B12: 0 | C12: =19*Premissas!$B$5 -> 104.5 | D12: Opcional | E12: ~US$ 19/mês se passar do limite gratuito. Conferir netlify.com/pricing.
A13: Resend (e-mails de login e lembretes) | B13: 0 | C13: =20*Premissas!$B$5 -> 110 | D13: Sim | E13: ~US$ 20/mês (50 mil e-mails). Conferir resend.com/pricing.
A14: Suporte e atendimento (WhatsApp Business/ChatFyre) | B14: 0 | C14: 0 | D14: Opcional | E14: Preencha se usar uma ferramenta paga.
A15: Marketing (aquisição de clientes) | B15: 0 | C15: =Premissas!$B$22 -> 1000 | D15: Opcional | E15: Puxado da aba Premissas.
A16: TOTAL | B16: =SUM(B5:B15) -> 2490 | C16: =SUM(C5:C15) -> 1602
A18: Custo variável por cliente (por mês)
A19: Item | B19: R$ por cliente/mês | E19: Observação
A20: IA (leads/mês × custo por lead) | B20: ='IA por lead'!$G$11 -> 44.715 | E20: Aba IA por lead.
A21: Taxa do gateway sobre a mensalidade | B21: =Premissas!$B$17*Premissas!$B$19+Premissas!$B$20 -> 6.3803 | E21: Asaas: % + tarifa fixa por cobrança.
A22: Imposto sobre a mensalidade | B22: =Premissas!$B$17*Premissas!$B$21 -> 11.82 | E22: Simples Nacional.
A23: Banco, e-mail e servidor por usuário (rateio) | B23: 1 | E23: Estimativa de uso adicional por cliente.
A24: Custo variável por cliente | B24: =SUM(B20:B23) -> 63.9153
A26: Resultado mensal com a meta de clientes
A27: Preço do plano (R$/mês) | B27: =Premissas!$B$17 -> 197
A28: Margem de contribuição por cliente (R$) | B28: =B27-B24 -> 133.0847
A29: Margem de contribuição (%) | B29: =IFERROR(B28/B27,0) -> 0.67555685
A30: Clientes pagantes | B30: =Premissas!$B$18 -> 30
A31: Receita mensal (R$) | B31: =B27*B30 -> 5910
A32: Custo variável total (R$) | B32: =B24*B30 -> 1917.459
A33: Custos fixos mensais (R$) | B33: =C16 -> 1602
A34: Lucro mensal (R$) | B34: =B31-B32-B33 -> 2390.541
A35: Clientes para empatar (ponto de equilíbrio) | B35: =IFERROR(ROUNDUP(B33/B28,0),0) -> 13
A36: Investimento inicial (R$) | B36: =B16 -> 2490
A37: Meses para recuperar o investimento | B37: =IF(B34>0,ROUNDUP(B36/B34,0),"Sem lucro ainda") -> 2

Sheet Fontes e notas
A1: Fontes e observações
A3: • Preços da IA: tabela da Anthropic (Claude Sonnet 5.5: US$ 2 / US$ 10; Claude Haiku 4.5: US$ 1 / US$ 5 por milhão de tokens), referência cacheada em 25/09/2026.
A4: • Supabase: Free US$ 0 (pausa após 7 dias sem uso); Pro US$ 25/mês. Fontes: makerkit.dev/blog/saas/supabase-pricing e jetadmin.io (guias 2026). Conferir supabase.com/pricing.
A5: • Netlify e Resend: valores de referência não confirmados nesta pesquisa. Conferir netlify.com/pricing e resend.com/pricing antes de contratar.
A6: • Asaas: as taxas oficiais não foram encontradas na pesquisa; os valores são estimativas de mercado. Conferir a tabela em asaas.com.
A7: • Instagram: a API de mensagens só permite responder quem falou primeiro, numa janela de 24h, e exige App Review para produção. Fonte: developers.facebook.com (Instagram Messaging).
A8: • Empresa, contador, advogado e INPI: estimativas. Peça orçamento a um contador e a um advogado.
A9: • O desenvolvimento é feito pelo Claude dentro da sua assinatura atual, por isso não aparece como custo extra.
A10: • Todas as fórmulas recalculam ao mudar a aba Premissas.
